mediaamp/http.py
mediaamp/exceptions.py
mediaamp/services.py
mediaamp/__init__.py
mediaamp/utils.py
mediaampy-0.2.8.dist-info/METADATA
mediaampy-0.2.8.dist-info/metadata.json
mediaampy-0.2.8.dist-info/DESCRIPTION.rst
mediaampy-0.2.8.dist-info/RECORD
mediaampy-0.2.8.dist-info/top_level.txt
mediaampy-0.2.8.dist-info/WHEEL
