Metadata-Version: 2.0
Name: mediaampy
Version: 0.2.8
Summary: HTTP Client for the MediaAmp/MPX API
Home-page: https://github.com/cordmata/mediaampy
Author: Matt Cordial
Author-email: UNKNOWN
License: Apache 2.0
Keywords: MediaAmp,thePlatform
Platform: UNKNOWN
Classifier: Development Status :: 3 - Alpha
Classifier: Intended Audience :: Developers
Classifier: Natural Language :: English
Classifier: License :: OSI Approved :: Apache Software License
Classifier: Programming Language :: Python
Classifier: Programming Language :: Python :: 2.7
Classifier: Programming Language :: Python :: 3
Classifier: Programming Language :: Python :: 3.2
Classifier: Programming Language :: Python :: 3.3
Classifier: Programming Language :: Python :: 3.4
Classifier: Topic :: Multimedia :: Sound/Audio
Classifier: Topic :: Multimedia :: Video
Requires-Dist: requests
Requires-Dist: blinker
Requires-Dist: pytz
